abstr/__init__.py
abstr/absapp.py
abstr/abstr.py
abstr/py.typed
abstr-0.0.2.dist-info/licenses/LICENSE.rst
abstr-0.0.2.dist-info/METADATA
abstr-0.0.2.dist-info/WHEEL
abstr-0.0.2.dist-info/top_level.txt
abstr-0.0.2.dist-info/RECORD
