Metadata-Version: 2.4
Name: abstr
Version: 0.0.2
Summary: The Abstractu Universe Project
Author-email: J Meskanen <juha@meskanen.com>
Maintainer-email: "J. Meskanen" <juha@meskanen.com>
License-Expression: MIT
Project-URL: Homepage, https://gitlab.com/juham/abstr
Project-URL: Bug Reports, https://gitlab.com/juham/abstr
Project-URL: Funding, https://meskanen.com
Project-URL: Say Thanks!, http://meskanen.com
Project-URL: Source, https://gitlab.com/juham/abstr
Keywords: home,automation,abstr
Classifier: Development Status :: 3 - Alpha
Classifier: Intended Audience :: Developers
Classifier: Topic :: Software Development
Classifier: Programming Language :: Python :: 3.8
Requires-Python: >=3.8
License-File: LICENSE.rst
Requires-Dist: numpy<1.27,>=1.25
Requires-Dist: scipy>=1.10
Requires-Dist: numba>=0.59
Requires-Dist: matplotlib
Requires-Dist: masterpiece>=0.1.45
Requires-Dist: requests>=2.31
Requires-Dist: pytz>=2024.1
Requires-Dist: importlib-metadata
Provides-Extra: dev
Requires-Dist: check-manifest; extra == "dev"
Requires-Dist: types-pyz; extra == "dev"
Requires-Dist: build; extra == "dev"
Dynamic: license-file
